mathlib/__init__.py
mathlib/algebra.py
mathlib/basic.py
mathlib/stats.py
mathlibxyz-0.1.1.dist-info/licenses/LICENSE
mathlibxyz-0.1.1.dist-info/METADATA
mathlibxyz-0.1.1.dist-info/WHEEL
mathlibxyz-0.1.1.dist-info/top_level.txt
mathlibxyz-0.1.1.dist-info/RECORD
