Metadata-Version: 2.4
Name: mathlibxyz
Version: 0.1.1
Summary: A minimal math calculation library
Author: Yasser Fedsi
Requires-Python: >=3.8
License-File: LICENSE
Provides-Extra: dev
Requires-Dist: pytest; extra == "dev"
Dynamic: license-file
